tsico2.py
tsico2-0.0.4.dist-info/METADATA
tsico2-0.0.4.dist-info/WHEEL
tsico2-0.0.4.dist-info/entry_points.txt
tsico2-0.0.4.dist-info/top_level.txt
tsico2-0.0.4.dist-info/RECORD
