Metadata-Version: 2.1
Name: tsico2
Version: 0.0.4
Summary: A package for visualizing TSI and CO2 with r2 and p-value
Home-page: https://github.com/y-takefuji/tsico2
Author: yoshiyasu takefuji
Author-email: takefuji@keio.jp
License: UNKNOWN
Project-URL: Bug Tracker, https://github.com/y-takefuji/tsico2
Platform: UNKNOWN
Classifier: Programming Language :: Python :: 3
Classifier: License :: OSI Approved :: MIT License
Classifier: Operating System :: OS Independent
Requires-Python: >=3.8
